fennomix_mhc/.DS_Store
fennomix_mhc/__init__.py
fennomix_mhc/cli.py
fennomix_mhc/mhc_binding_model.py
fennomix_mhc/mhc_binding_retriever.py
fennomix_mhc/mhc_utils.py
fennomix_mhc/pipeline_api.py
fennomix_mhc/plotting_utils.py
fennomix_mhc/tda_fmm.py
fennomix_mhc/__pycache__/__init__.cpython-311.pyc
fennomix_mhc/__pycache__/__init__.cpython-39.pyc
fennomix_mhc/__pycache__/cli.cpython-311.pyc
fennomix_mhc/__pycache__/cli.cpython-39.pyc
fennomix_mhc/__pycache__/mhc_binding_model.cpython-311.pyc
fennomix_mhc/__pycache__/mhc_binding_retriever.cpython-311.pyc
fennomix_mhc/__pycache__/mhc_utils.cpython-311.pyc
fennomix_mhc/__pycache__/pipeline_api.cpython-311.pyc
fennomix_mhc/__pycache__/pipeline_api.cpython-39.pyc
fennomix_mhc/__pycache__/plotting_utils.cpython-311.pyc
fennomix_mhc/__pycache__/tda_fmm.cpython-311.pyc
fennomix_mhc/constants/__init__.py
fennomix_mhc/constants/_const.py
fennomix_mhc/constants/global_settings.yaml
fennomix_mhc/constants/__pycache__/__init__.cpython-311.pyc
fennomix_mhc/constants/__pycache__/_const.cpython-311.pyc
fennomix_mhc-0.0.1.dev0.dist-info/licenses/LICENSE
fennomix_mhc-0.0.1.dev0.dist-info/METADATA
fennomix_mhc-0.0.1.dev0.dist-info/WHEEL
fennomix_mhc-0.0.1.dev0.dist-info/entry_points.txt
fennomix_mhc-0.0.1.dev0.dist-info/top_level.txt
fennomix_mhc-0.0.1.dev0.dist-info/RECORD
