Metadata-Version: 2.4
Name: fennomix-mhc
Version: 0.0.1.dev0
Summary: FennOmix-MHC
Author-email: Wen-Feng Zeng <zengwenfeng@westlake.edu.cn>, Jin-Tao Cheng <1274873858@qq.com>
Maintainer-email: Wen-Feng Zeng <zengwenfeng@westlake.edu.cn>, Jin-Tao Cheng <1274873858@qq.com>
Project-URL: Homepage, https://fennomix.lab.westlake.edu.cn
Project-URL: Documentation, https://readthedocs.org
Project-URL: Repository, https://github.com/FennOmix/fennomix.mhc.git
Project-URL: Bug Tracker, https://github.com/FennOmix/fennomix.mhc/issues
Project-URL: Changelog, https://github.com/FennOmix/fennomix.mhc/blob/main/CHANGELOG.md
Keywords: contrastive learning,protein language model,immunopeptidomics,mass spectrometry,HLA,MHC,peptide-MHC binding prediction
Classifier: Development Status :: 1 - Planning
Classifier: Programming Language :: Python
Requires-Python: <3.12,>=3.10
License-File: LICENSE
Requires-Dist: alphabase
Requires-Dist: peptdeep
Requires-Dist: pydivsufsort
Requires-Dist: fair-esm
Requires-Dist: matplotlib
Requires-Dist: pre-commit
Requires-Dist: click
Requires-Dist: faiss-cpu
Requires-Dist: logomaker
Requires-Dist: plotly
Requires-Dist: umap-learn
Provides-Extra: stable
Provides-Extra: tests
Requires-Dist: coverage; extra == "tests"
Requires-Dist: coverage-badge; extra == "tests"
Requires-Dist: pytest; extra == "tests"
Requires-Dist: neptune; extra == "tests"
Provides-Extra: docs
Provides-Extra: development
Requires-Dist: jupyter; extra == "development"
Requires-Dist: jupyter_contrib_nbextensions; extra == "development"
Requires-Dist: bump-my-version; extra == "development"
Requires-Dist: pipdeptree; extra == "development"
Requires-Dist: ipykernel; extra == "development"
Requires-Dist: pre-commit==3.7.0; extra == "development"
Requires-Dist: neptune; extra == "development"
Requires-Dist: coverage; extra == "development"
Requires-Dist: coverage-badge; extra == "development"
Requires-Dist: pytest; extra == "development"
Requires-Dist: neptune; extra == "development"
Dynamic: license-file
